Metadata-Version: 1.0
Name: CEAD
Version: 0.1
Summary: conda environment automation deployment
Home-page: https://github.com/g-lyc/CEAD
Author: liyc
Author-email: liyichen2015@gmail.com
License: liyc
Platform: UNKNOWN
